url_instax/__init__.py
url_instax/cli.py
url_instax/config.py
url_instax/log.py
url_instax/main.py
url_instax/mcp.py
url_instax/web_app.py
url_instax/routers/__init__.py
url_instax/routers/api/__init__.py
url_instax/routers/api/v1/__init__.py
url_instax/routers/api/v1/screenshot.py
url_instax-0.1.3.dist-info/METADATA
url_instax-0.1.3.dist-info/WHEEL
url_instax-0.1.3.dist-info/entry_points.txt
url_instax-0.1.3.dist-info/licenses/LICENSE
url_instax-0.1.3.dist-info/RECORD
