Metadata-Version: 2.4
Name: url-instax
Version: 0.1.3
Summary: Screenshot for web page.
Project-URL: Homepage, https://wh1isper.github.io/url-instax/
Project-URL: Repository, https://github.com/wh1isper/url-instax
Project-URL: Documentation, https://wh1isper.github.io/url-instax/
Author-email: Wh1isper <jizhongsheng957@gmail.com>
License-File: LICENSE
Keywords: python
Classifier: Intended Audience :: Developers
Classifier: Programming Language :: Python
Classifier: Programming Language :: Python :: 3
Classifier: Programming Language :: Python :: 3.10
Classifier: Programming Language :: Python :: 3.11
Classifier: Programming Language :: Python :: 3.12
Classifier: Programming Language :: Python :: 3.13
Classifier: Topic :: Software Development :: Libraries :: Python Modules
Requires-Python: <4.0,>=3.10
Requires-Dist: aiocache>=0.12.3
Requires-Dist: click>=8.1.8
Requires-Dist: fastapi>=0.115.12
Requires-Dist: httpx>=0.28.1
Requires-Dist: loguru>=0.7.3
Requires-Dist: mcp[cli]>=1.6.0
Requires-Dist: playwright>=1.51.0
Requires-Dist: pydantic>=2.11.3
Requires-Dist: python-dotenv>=1.1.0
Requires-Dist: uvicorn[standard]>=0.34.2
